kobukidriver/Kobuki.py
kobukidriver/__init__.py
kobukidriver-0.0.1.dist-info/LICENSE
kobukidriver-0.0.1.dist-info/METADATA
kobukidriver-0.0.1.dist-info/WHEEL
kobukidriver-0.0.1.dist-info/top_level.txt
kobukidriver-0.0.1.dist-info/RECORD
