Metadata-Version: 2.1
Name: kobukidriver
Version: 0.0.1
Summary: A simple python driver  for Kobuki mobile robot
Home-page: UNKNOWN
Author: Parthasarathi,Ram sankar,Ganesh
Author-email: parthasarathi_s@tce.edu,ramsankarcsr@gmail.com,ganeshma2015@tce.edu
License: UNKNOWN
Platform: UNKNOWN
Classifier: Topic :: Communications
Classifier: Topic :: Software Development
Classifier: Topic :: Utilities
Classifier: Intended Audience :: Developers
Classifier: Programming Language :: Python :: 3
Classifier: License :: OSI Approved :: GNU General Public License v3 (GPLv3)
Classifier: Operating System :: OS Independent
Requires-Python: >=3.6
